LICENSE.txt
README.md
setup.py
emlhound/__init__.py
emlhound/config.py
emlhound/emlhound.py
emlhound/vaultman.py
emlhound.egg-info/PKG-INFO
emlhound.egg-info/SOURCES.txt
emlhound.egg-info/dependency_links.txt
emlhound.egg-info/requires.txt
emlhound.egg-info/top_level.txt