Metadata-Version: 2.1
Name: emlhound
Version: 0.2
Summary: EML Forensics Application
Home-page: https://github.com/needmorecowbell/EMLHound
Author: needmorecowbell
Author-email: amusciano@gmail.com
License: MIT
Download-URL: https://github.com/needmorecowbell/EMLHound/archive/refs/tags/0.2.tar.gz
Keywords: EML
Platform: UNKNOWN
Classifier: Development Status :: 3 - Alpha
Classifier: Intended Audience :: Developers
Classifier: Topic :: Software Development :: Build Tools
Classifier: License :: OSI Approved :: MIT License
Classifier: Programming Language :: Python :: 3.10
License-File: LICENSE.txt
